sutton_signwriting_font/__init__.py
sutton_signwriting_font/datatypes.py
sutton_signwriting_font/db/iswa2010.db
sutton_signwriting_font/db.py
sutton_signwriting_font/fsw.py
sutton_signwriting_font/py.typed
sutton_signwriting_font/swu.py
sutton_signwriting_font-1.0.1.dist-info/METADATA
sutton_signwriting_font-1.0.1.dist-info/WHEEL
sutton_signwriting_font-1.0.1.dist-info/licenses/LICENSE
sutton_signwriting_font-1.0.1.dist-info/RECORD
