Metadata-Version: 2.4
Name: sutton-signwriting-font
Version: 1.0.1
Summary: Python tools for Sutton SignWriting font visualization in SVG and PNG.
License: MIT
License-File: LICENSE
Keywords: signwriting,fsw,swu,sign-language,sutton-signwriting,svg,png,visualization
Author: Steve Slevinski
Author-email: Slevinski@signwriting.org
Requires-Python: >=3.11,<4.0
Classifier: Intended Audience :: Developers
Classifier: License :: OSI Approved :: MIT License
Classifier: Programming Language :: Python :: 3
Classifier: Programming Language :: Python :: 3.11
Classifier: Programming Language :: Python :: 3.12
Classifier: Programming Language :: Python :: 3.13
Classifier: Programming Language :: Python :: 3.14
Classifier: Topic :: Multimedia :: Graphics :: Graphics Conversion
Classifier: Topic :: Scientific/Engineering :: Information Analysis
Classifier: Topic :: Text Processing :: Linguistic
Requires-Dist: cairosvg (>=2.7.1,<3.0.0)
Requires-Dist: sutton-signwriting-core (>=1.1.2,<2.0.0)
Project-URL: Documentation, https://sutton-signwriting.io/font-py
Project-URL: Homepage, https://github.com/sutton-signwriting/font-py
Project-URL: Repository, https://github.com/sutton-signwriting/font-py
